README.md
setup.py
PySide6_Fluent_Widgets_TextInputDialog.egg-info/PKG-INFO
PySide6_Fluent_Widgets_TextInputDialog.egg-info/SOURCES.txt
PySide6_Fluent_Widgets_TextInputDialog.egg-info/dependency_links.txt
PySide6_Fluent_Widgets_TextInputDialog.egg-info/requires.txt
PySide6_Fluent_Widgets_TextInputDialog.egg-info/top_level.txt
qfluentwidgets_textinputdialog/__init__.py
qfluentwidgets_textinputdialog/text_input_dialog.py