Metadata-Version: 2.1
Name: PySide6-Fluent-Widgets-TextInputDialog
Version: 0.0.2
Summary: It provides a simple way to create text input dialogs.
Author: Chamiko
Author-email: Chamiko@foxmail.com
Keywords: PySide6,Fluent-Widgets,Widget,Python
Classifier: Development Status :: 1 - Planning
Requires-Python: >=3.6, <3.12
Requires-Dist: PySide6-Fluent-Widgets
